README.md
setup.py
Topsis_Nikhil_101803670.egg-info/PKG-INFO
Topsis_Nikhil_101803670.egg-info/SOURCES.txt
Topsis_Nikhil_101803670.egg-info/dependency_links.txt
Topsis_Nikhil_101803670.egg-info/requires.txt
Topsis_Nikhil_101803670.egg-info/top_level.txt
Topsis_pckg/__init__.py
Topsis_pckg/topsis.py
topsis_Nikhil_101803670.egg-info/PKG-INFO
topsis_Nikhil_101803670.egg-info/SOURCES.txt
topsis_Nikhil_101803670.egg-info/dependency_links.txt
topsis_Nikhil_101803670.egg-info/requires.txt
topsis_Nikhil_101803670.egg-info/top_level.txt
topsis_pckg/__init__.py
topsis_pckg/topsis.py